{
  "version": "7",
  "dialect": "postgresql",
  "entries": [
    {
      "idx": 0,
      "version": "7",
      "when": 1763751746267,
      "tag": "0000_wild_lila_cheney",
      "breakpoints": true
    },
    {
      "idx": 1,
      "version": "7",
      "when": 1763919519913,
      "tag": "0001_wooden_luke_cage",
      "breakpoints": true
    },
    {
      "idx": 2,
      "version": "7",
      "when": 1763919751648,
      "tag": "0002_talented_hobgoblin",
      "breakpoints": true
    },
    {
      "idx": 3,
      "version": "7",
      "when": 1764930622353,
      "tag": "0003_closed_longshot",
      "breakpoints": true
    },
    {
      "idx": 4,
      "version": "7",
      "when": 1765546785791,
      "tag": "0004_smiling_jimmy_woo",
      "breakpoints": true
    }
  ]
}